price_forecast_suite_package/__init__.py
price_forecast_suite_package/auto_model.py
price_forecast_suite_package/shandong.py
price_forecast_suite_package/shanxi.py
price_forecast_suite_package/shanxi_test.py
price_forecast_suite_package/suite_base.py
price_forecast_suite_package/suite_class_entry.py
price_forecast_suite_package/suite_data.py
price_forecast_suite_package/suite_feature_engineer_sg.py
price_forecast_suite_package/suite_feature_engineer_tt.py
price_forecast_suite_package/suite_model.py
price_forecast_suite_package/usep_fr.py
price_forecast_suite_package/usep_long.py
price_forecast_suite_package/usep_reserve.py
price_forecast_suite_package/usep_short.py
tests/__init__.py
tests/test_model.py
price_forecast_suite_package-0.1.65.dist-info/LICENSE
price_forecast_suite_package-0.1.65.dist-info/METADATA
price_forecast_suite_package-0.1.65.dist-info/WHEEL
price_forecast_suite_package-0.1.65.dist-info/top_level.txt
price_forecast_suite_package-0.1.65.dist-info/RECORD
